README.rst
setup.cfg
setup.py
av2hdf5/__init__.py
av2hdf5.egg-info/PKG-INFO
av2hdf5.egg-info/SOURCES.txt
av2hdf5.egg-info/dependency_links.txt
av2hdf5.egg-info/entry_points.txt
av2hdf5.egg-info/requires.txt
av2hdf5.egg-info/top_level.txt
av2hdf5.egg-info/zip-safe