Metadata-Version: 1.1
Name: av2hdf5
Version: 1.0
Summary: Extract video frames into an HDF5 file
Home-page: https://github.com/rjw57/av2hdf5
Author: Rich Wareham
Author-email: rich.av2hdf5@richwareham.com
License: BSD
Platform: UNKNOWN
Classifier: Development Status :: 2 - Pre-Alpha
Classifier: Intended Audience :: Developers
Classifier: License :: OSI Approved :: BSD License
Classifier: Natural Language :: English
Classifier: Programming Language :: Python :: 2
Classifier: Programming Language :: Python :: 2.6
Classifier: Programming Language :: Python :: 2.7
Classifier: Programming Language :: Python :: 3
Classifier: Programming Language :: Python :: 3.3
